greyhorse_web/__init__.py
greyhorse_web/common.py
greyhorse_web/py.typed
greyhorse_web/schemas.py
greyhorse_web/grpc/__init__.py
greyhorse_web/grpc/betterproto.py
greyhorse_web/http/__init__.py
greyhorse_web/http/fastapi/__init__.py
greyhorse_web/http/fastapi/controller.py
greyhorse_web/http/fastapi/deps.py
greyhorse_web/http/fastapi/factory.py
greyhorse_web/http/fastapi/service.py
greyhorse_web/http/fastapi/utils.py
greyhorse_web/http/strawberry/__init__.py
greyhorse_web/http/strawberry/context.py
greyhorse_web/http/strawberry/extensions.py
greyhorse_web/http/strawberry/mixins.py
greyhorse_web/http/strawberry/pagination.py
greyhorse_web/http/strawberry/router.py
greyhorse_web/http/strawberry/types.py
greyhorse_web/servers/__init__.py
greyhorse_web/servers/hypercorn.py
greyhorse_web/servers/uvicorn.py
greyhorse_web-0.4.26.dist-info/METADATA
greyhorse_web-0.4.26.dist-info/WHEEL
greyhorse_web-0.4.26.dist-info/RECORD
